flex_eav/__init__.py
flex_eav/admin.py
flex_eav/apps.py
flex_eav/eav_validator.py
flex_eav/models.py
flex_eav/tests.py
flex_eav/utils.py
flex_eav/views.py
flex_eav/migrations/__init__.py
django_flex_eav-0.0.7.dist-info/AUTHORS.rst
django_flex_eav-0.0.7.dist-info/LICENSE
django_flex_eav-0.0.7.dist-info/METADATA
django_flex_eav-0.0.7.dist-info/WHEEL
django_flex_eav-0.0.7.dist-info/top_level.txt
django_flex_eav-0.0.7.dist-info/RECORD
