Metadata-Version: 2.1
Name: django-flex-eav
Version: 0.0.7
Summary: Django project implementing the EAV pattern for the database models
Author-email: Saman Zand Haghighi <samanzandh@gmail.com>, Ali Avani <ali.avani@outlook.com>
Maintainer-email: Saman Zand Haghighi <samanzandh@gmail.com>, Ali Avani <ali.avani@outlook.com>
License: MIT license
Project-URL: bugs, https://github.com/ali-avani/django-flex-eav/issues
Project-URL: changelog, https://github.com/ali-avani/django-flex-eav/blob/master/changelog.md
Project-URL: homepage, https://github.com/ali-avani/django-flex-eav
License-File: LICENSE
License-File: AUTHORS.rst
Provides-Extra: dev
Requires-Dist: coverage; extra == "dev"
Requires-Dist: mypy; extra == "dev"
Requires-Dist: pytest; extra == "dev"
Requires-Dist: ruff; extra == "dev"
